pipewire_filtertools-0.3.0.data/purelib/_custom_build.py
pipewire_filtertools-0.3.0.data/purelib/pipewire_filtertools/__init__.py
pipewire_filtertools-0.3.0.data/purelib/pipewire_filtertools/_pipewire_filtertools.py
pipewire_filtertools-0.3.0.data/purelib/pipewire_filtertools/libpipewire-filtertools.so
pipewire_filtertools-0.3.0.data/purelib/pipewire_filtertools/pipewire-filtertools/context.h
pipewire_filtertools-0.3.0.data/purelib/pipewire_filtertools/pipewire-filtertools/mainloop.c
pipewire_filtertools-0.3.0.data/purelib/pipewire_filtertools/pipewire-filtertools/pipewire-filtertools.h
pipewire_filtertools-0.3.0.data/purelib/pipewire_filtertools/pipewire-filtertools/retargeting.c
pipewire_filtertools-0.3.0.data/purelib/pipewire_filtertools/pipewire-filtertools/retargeting.h
pipewire_filtertools-0.3.0.dist-info/licenses/LICENSE
pipewire_filtertools-0.3.0.dist-info/METADATA
pipewire_filtertools-0.3.0.dist-info/WHEEL
pipewire_filtertools-0.3.0.dist-info/top_level.txt
pipewire_filtertools-0.3.0.dist-info/RECORD
