Metadata-Version: 2.4
Name: pipewire-filtertools
Version: 0.3.0
Summary: PipeWire filter tools C library and Python bindings
Author-email: develOseven <devel.oseven@gmail.com>
License-Expression: MIT
Project-URL: Homepage, https://github.com/develOseven/pipewire-filtertools
Project-URL: Issues, https://github.com/develOseven/pipewire-filtertools/issues
Classifier: Programming Language :: Python :: 3
Classifier: Operating System :: POSIX :: Linux
License-File: LICENSE
Dynamic: license-file
